django_umami/__init__.py
django_umami/apps.py
django_umami/core.py
django_umami/decorators.py
django_umami/settings.py
django_umami/tests.py
django_umami/urls.py
django_umami/utils.py
django_umami/wsgi.py
django_umami-0.3.0.dist-info/LICENSE
django_umami-0.3.0.dist-info/METADATA
django_umami-0.3.0.dist-info/WHEEL
django_umami-0.3.0.dist-info/top_level.txt
django_umami-0.3.0.dist-info/RECORD
